nudeclient/__init__.py
nudeclient/client.py
nudeclient-1.0.1.dist-info/METADATA
nudeclient-1.0.1.dist-info/WHEEL
nudeclient-1.0.1.dist-info/top_level.txt
nudeclient-1.0.1.dist-info/RECORD
