Metadata-Version: 2.1
Name: nudeclient
Version: 1.0.1
Summary: Python tfserving client for nudenet
Home-page: https://github.com/bedapudi6788/NudeNet
Author: BEDAPUDI PRANEETH
Author-email: praneethbedapudi@gmail.com
License: GPLv3
Platform: UNKNOWN
Classifier: License :: OSI Approved :: GNU General Public License v3 (GPLv3)
Classifier: Programming Language :: Python
Classifier: Programming Language :: Python :: 3
Classifier: Programming Language :: Python :: 3.6
Classifier: Programming Language :: Python :: Implementation :: CPython
Classifier: Programming Language :: Python :: Implementation :: PyPy
Requires-Python: >=3.5.0
Requires-Dist: Pillow
Requires-Dist: tensorflow-serving-api (==1.14.0)
